Workbook

Sheet Export Summary
B3: This document was exported from Numbers. Each table was converted to an Excel worksheet. All other objects on each Numbers sheet were placed on separate worksheets. Please be aware that formula calculations may differ in Excel.
B7: Numbers Sheet Name | C7: Numbers Table Name | D7: Excel Worksheet Name
B9: Headline_Master
C10: Table 1 | D10: Headline_Master
B11: Source_Metadata
C12: Table 1 | D12: Source_Metadata

Sheet Headline_Master
A1: Headline_ID | B1: Source_Name | C1: Date | D1: Headline_Text | E1: Category | F1: Engagement_Count | G1: Source_Trust_Score | H1: Viral_Status | I1: Headline_Length | J1: Impact_Score | K1: Reach_Percentage | L1: Reliability_Check
A2: H-001 | B2: TechCrunch | C2: 46064 | D2: xAI Lays Out Interplanetary Ambitions in Public All-Hands Meeting | E2: Technology | F2: 556 | G2: =IFERROR(VLOOKUP(B2,Source_Metadata!$A$2:$C$8,3,FALSE),"") -> 8 | H2: =IF(F2>1500,"High",IF(F2>500,"Medium","Low")) -> Medium | I2: =LEN(D2) -> 65 | J2: =(F2 * G2) -> 4448 | K2: =(F2 / 2500) -> 0.2224 | L2: =IF(G2 < 9, "Verify", "Trusted") -> Verify
A3: H-002 | B3: TechCrunch | C3: 46065 | D3: AI Inference Startup Modal Labs in Talks to Raise at $2.5B Valuation | E3: Technology | F3: 202 | G3: =IFERROR(VLOOKUP(B3,Source_Metadata!$A$2:$C$8,3,FALSE),"") -> 8 | H3: =IF(F3>1500,"High",IF(F3>500,"Medium","Low")) -> Low | I3: =LEN(D3) -> 68 | J3: =(F3 * G3) -> 1616 | K3: =(F3 / 2500) -> 0.0808 | L3: =IF(G3 < 9, "Verify", "Trusted") -> Verify
A4: H-003 | B4: TechCrunch | C4: 46066 | D4: OpenAI Disbands Mission Alignment Team Which Focused on Safe and Trustworthy AI Development | E4: Technology | F4: 1226 | G4: =IFERROR(VLOOKUP(B4,Source_Metadata!$A$2:$C$8,3,FALSE),"") -> 8 | H4: =IF(F4>1500,"High",IF(F4>500,"Medium","Low")) -> Medium | I4: =LEN(D4) -> 91 | J4: =(F4 * G4) -> 9808 | K4: =(F4 / 2500) -> 0.4904 | L4: =IF(G4 < 9, "Verify", "Trusted") -> Verify
A5: H-004 | B5: TechCrunch | C5: 46067 | D5: Apple's Siri Revamp Reportedly Delayed Again as Internal Timelines Slip | E5: Technology | F5: 1103 | G5: =IFERROR(VLOOKUP(B5,Source_Metadata!$A$2:$C$8,3,FALSE),"") -> 8 | H5: =IF(F5>1500,"High",IF(F5>500,"Medium","Low")) -> Medium | I5: =LEN(D5) -> 71 | J5: =(F5 * G5) -> 8824 | K5: =(F5 / 2500) -> 0.4412 | L5: =IF(G5 < 9, "Verify", "Trusted") -> Verify
A6: H-005 | B6: TechCrunch | C6: 46068 | D6: Uber Eats Launches AI Assistant to Help Users Build Grocery Carts Automatically | E6: Technology | F6: 1014 | G6: =IFERROR(VLOOKUP(B6,Source_Metadata!$A$2:$C$8,3,FALSE),"") -> 8 | H6: =IF(F6>1500,"High",IF(F6>500,"Medium","Low")) -> Medium | I6: =LEN(D6) -> 79 | J6: =(F6 * G6) -> 8112 | K6: =(F6 / 2500) -> 0.4056 | L6: =IF(G6 < 9, "Verify", "Trusted") -> Verify
A7: H-006 | B7: TechCrunch | C7: 46069 | D7: Microsoft Says Hackers Are Exploiting Critical Zero-Day Bugs to Target Windows and Office Users | E7: Technology | F7: 671 | G7: =IFERROR(VLOOKUP(B7,Source_Metadata!$A$2:$C$8,3,FALSE),"") -> 8 | H7: =IF(F7>1500,"High",IF(F7>500,"Medium","Low")) -> Medium | I7: =LEN(D7) -> 95 | J7: =(F7 * G7) -> 5368 | K7: =(F7 / 2500) -> 0.2684 | L7: =IF(G7 < 9, "Verify", "Trusted") -> Verify
A8: H-007 | B8: TechCrunch | C8: 46070 | D8: Amazon Acquires Satellite Operator Globalstar for $11.57 Billion to Expand Project Kuiper | E8: Technology | F8: 519 | G8: =IFERROR(VLOOKUP(B8,Source_Metadata!$A$2:$C$8,3,FALSE),"") -> 8 | H8: =IF(F8>1500,"High",IF(F8>500,"Medium","Low")) -> Medium | I8: =LEN(D8) -> 89 | J8: =(F8 * G8) -> 4152 | K8: =(F8 / 2500) -> 0.2076 | L8: =IF(G8 < 9, "Verify", "Trusted") -> Verify
A9: H-008 | B9: TechCrunch | C9: 46071 | D9: Blue Origin's New Glenn Rocket Successfully Reuses First-Stage Booster for First Time | E9: Technology | F9: 2333 | G9: =IFERROR(VLOOKUP(B9,Source_Metadata!$A$2:$C$8,3,FALSE),"") -> 8 | H9: =IF(F9>1500,"High",IF(F9>500,"Medium","Low")) -> High | I9: =LEN(D9) -> 85 | J9: =(F9 * G9) -> 18664 | K9: =(F9 / 2500) -> 0.9332 | L9: =IF(G9 < 9, "Verify", "Trusted") -> Verify
A10: H-009 | B10: TechCrunch | C10: 46072 | D10: Palantir CEO's Culture War Post Puts Company's Identity at Center of Defense Tech Debate | E10: Technology | F10: 456 | G10: =IFERROR(VLOOKUP(B10,Source_Metadata!$A$2:$C$8,3,FALSE),"") -> 8 | H10: =IF(F10>1500,"High",IF(F10>500,"Medium","Low")) -> Low | I10: =LEN(D10) -> 88 | J10: =(F10 * G10) -> 3648 | K10: =(F10 / 2500) -> 0.1824 | L10: =IF(G10 < 9, "Verify", "Trusted") -> Verify
A11: H-010 | B11: TechCrunch | C11: 46073 | D11: DOJ Says Trenchant Boss Sold Exploits to Russian Broker Capable of Accessing Millions of Devices | E11: Technology | F11: 1828 | G11: =IFERROR(VLOOKUP(B11,Source_Metadata!$A$2:$C$8,3,FALSE),"") -> 8 | H11: =IF(F11>1500,"High",IF(F11>500,"Medium","Low")) -> High | I11: =LEN(D11) -> 96 | J11: =(F11 * G11) -> 14624 | K11: =(F11 / 2500) -> 0.7312 | L11: =IF(G11 < 9, "Verify", "Trusted") -> Verify
A12: H-011 | B12: TechCrunch | C12: 46074 | D12: Why the Economics of Orbital AI Are So Brutal for Startups Chasing Space Infrastructure | E12: Technology | F12: 230 | G12: =IFERROR(VLOOKUP(B12,Source_Metadata!$A$2:$C$8,3,FALSE),"") -> 8 | H12: =IF(F12>1500,"High",IF(F12>500,"Medium","Low")) -> Low | I12: =LEN(D12) -> 87 | J12: =(F12 * G12) -> 1840 | K12: =(F12 / 2500) -> 0.092 | L12: =IF(G12 < 9, "Verify", "Trusted") -> Verify
A13: H-012 | B13: Wired | C13: 46075 | D13: Anthropic Introduces Claude Managed Agents for Deploying Autonomous AI in Production Environments | E13: Technology | F13: 222 | G13: =IFERROR(VLOOKUP(B13,Source_Metadata!$A$2:$C$8,3,FALSE),"") -> 8 | H13: =IF(F13>1500,"High",IF(F13>500,"Medium","Low")) -> Low | I13: =LEN(D13) -> 97 | J13: =(F13 * G13) -> 1776 | K13: =(F13 / 2500) -> 0.0888 | L13: =IF(G13 < 9, "Verify", "Trusted") -> Verify
... A61: H-060 | B61: European Commission | C61: 46123 | D61: EU Bans All Short-Term LNG and Pipeline Gas Contracts as Europe Accelerates Energy Independence Drive | E61: Global Politics | F61: 1957 | G61: =IFERROR(VLOOKUP(B61,Source_Metadata!$A$2:$C$8,3,FALSE),"") -> 9 | H61: =IF(F61>1500,"High",IF(F61>500,"Medium","Low")) -> High | I61: =LEN(D61) -> 101 | J61: =(F61 * G61) -> 17613 | K61: =(F61 / 2500) -> 0.7828 | L61: =IF(G61 < 9, "Verify", "Trusted") -> Trusted

Sheet Source_Metadata
A1: Source_Name | B1: Region | C1: Trust_Score | D1: Media_Type
A2: TechCrunch | B2: USA | C2: 8 | D2: Digital Media
A3: Wired | B3: USA | C3: 8 | D3: Digital Media
A4: Reuters | B4: Global | C4: 9 | D4: News Agency
A5: SEC | B5: USA | C5: 9 | D5: Government
A6: McKinsey | B6: Global | C6: 8 | D6: Research / Consulting
A7: BBC | B7: UK | C7: 9 | D7: Public Broadcaster
A8: European Commission | B8: EU | C8: 9 | D8: Government

Sheet Pivot Table 1
